LICENSE.txt
README.md
setup.py
dtu_toke/__init__.py
dtu_toke/functions.py
dtu_toke.egg-info/PKG-INFO
dtu_toke.egg-info/SOURCES.txt
dtu_toke.egg-info/dependency_links.txt
dtu_toke.egg-info/top_level.txt