Metadata-Version: 2.1
Name: dtu-toke
Version: 1.0
Summary: My first package
Author: toke.schaffer
License-File: LICENSE.txt
